stml.py
stml-0.1.6.dist-info/LICENSE
stml-0.1.6.dist-info/METADATA
stml-0.1.6.dist-info/WHEEL
stml-0.1.6.dist-info/top_level.txt
stml-0.1.6.dist-info/RECORD
