Metadata-Version: 2.1
Name: stml
Version: 0.1.6
Summary: Implement HTML with Indentation
Author: Vishal R
Keywords: stml,STML,indent HTML,simple text markup language
Classifier: Programming Language :: Python :: 3
Classifier: License :: OSI Approved :: MIT License
Classifier: Operating System :: OS Independent
Requires-Python: >=3.6
License-File: LICENSE
